tide/__init__.py
tide/__main__.py
tide/cli.py
tide/core.py
tide/gitutils.py
tide/py.typed
git_tide-0.2.1.dist-info/METADATA
git_tide-0.2.1.dist-info/WHEEL
git_tide-0.2.1.dist-info/entry_points.txt
git_tide-0.2.1.dist-info/RECORD
