Metadata-Version: 2.3
Name: git-tide
Version: 0.2.1
Summary: CLI for automated gitflow-style branching
Project-URL: Homepage, https://github.com/chadrik/git-tide
Author: Chad Dombrova, Matt Collie
Requires-Python: >=3.8
Requires-Dist: click
Requires-Dist: commitizen==3.16.0
Requires-Dist: tomli
Requires-Dist: typing-extensions
Provides-Extra: init
Requires-Dist: python-gitlab==4.8.0; extra == 'init'
Provides-Extra: test
Requires-Dist: pytest; extra == 'test'
